tests/__init__.py
tests/test_config.py
tests/test_location.py
tests/test_sun.py
weather/__init__.py
weather/__main__.py
weather/config/__init__.py
weather/config/settings.py
weather/services/__init__.py
weather/services/location.py
weather/services/sun.py
weather/services/weather.py
weather/templates/index.html
weather/view/__init__.py
weather/view/city.py
weather/view/home.py
async_weather_api-0.5.0.dist-info/LICENSE.md
async_weather_api-0.5.0.dist-info/METADATA
async_weather_api-0.5.0.dist-info/WHEEL
async_weather_api-0.5.0.dist-info/top_level.txt
async_weather_api-0.5.0.dist-info/RECORD
