Metadata-Version: 2.1
Name: async-weather-api
Version: 0.5.0
Summary: This project represents sample of asynchronous weather REST API that is build using quart (flask compatible API) python web microframework based on Asyncio
Home-page: https://github.com/vyahello/async-weather-api
Author: Volodymyr Yahello
Author-email: vyahello@gmail.com
License: UNKNOWN
Platform: UNKNOWN
Classifier: Programming Language :: Python :: 3.6
Classifier: Programming Language :: Python :: 3.7
Classifier: Programming Language :: Python :: 3.8
Classifier: License :: OSI Approved :: MIT License
Classifier: Operating System :: OS Independent
Requires-Python: >=3.6
Requires-Dist: quart (==0.6.15)
Requires-Dist: aiohttp (==3.6.2)
Requires-Dist: aiodns (==2.0.0)
Requires-Dist: cchardet (==2.1.5)
Requires-Dist: setuptools (==42.0.2)
Requires-Dist: wheel (==0.33.6)
Requires-Dist: twine (==3.1.1)
